LICENSE
README.md
setup.py
berluf_selen_2/__init__.py
berluf_selen_2.egg-info/PKG-INFO
berluf_selen_2.egg-info/SOURCES.txt
berluf_selen_2.egg-info/dependency_links.txt
berluf_selen_2.egg-info/requires.txt
berluf_selen_2.egg-info/top_level.txt
berluf_selen_2/modbus_impl/__init__.py
berluf_selen_2/modbus_impl/asyncio/__init__.py
berluf_selen_2/modbus_impl/asyncio/timer.py
berluf_selen_2/modbus_impl/pymodbus/__init__.py
berluf_selen_2/modbus_impl/pymodbus/memory.py
berluf_selen_2/modbus_impl/pymodbus/serial.py
berluf_selen_2/modbus_slave/__init__.py
berluf_selen_2/modbus_slave/device.py
berluf_selen_2/modbus_slave/func.py
berluf_selen_2/modbus_slave/intf.py
berluf_selen_2/modbus_slave/memory.py
berluf_selen_2/modbus_slave/memory_async.py
berluf_selen_2/modbus_slave/serial.py
berluf_selen_2/modbus_slave/timer.py
berluf_selen_2/modbus_slave/validator.py
berluf_selen_2/modbus_slave/observer_func/__init__.py
berluf_selen_2/modbus_slave/observer_func/callb.py
berluf_selen_2/modbus_slave/observer_func/func.py
berluf_selen_2/modbus_slave/tests/__init__.py
berluf_selen_2/modbus_slave/tests/dummies.py
berluf_selen_2/modbus_slave/tests/test_callb.py
berluf_selen_2/modbus_slave/tests/test_func.py
berluf_selen_2/modbus_slave/tests/test_memory.py
berluf_selen_2/modbus_slave/tests/test_validator.py
berluf_selen_2/recup/__init__.py
berluf_selen_2/recup/device.py
berluf_selen_2/recup/funcs.py
berluf_selen_2/recup/serial.py
berluf_selen_2/recup/tests/__init__.py
berluf_selen_2/recup/tests/test_device.py
berluf_selen_2/recup/tests/test_func.py