Metadata-Version: 2.1
Name: berluf_selen_2
Version: 0.1.3
Summary: Package for controlling Berluf Selen 2 recuperator.
Home-page: https://github.com/3p3v/berluf_selen_2
Author: Adam Golecki
Author-email: adam@golecki.pl
License: MIT
Classifier: Programming Language :: Python :: 3
Classifier: License :: OSI Approved :: MIT License
Classifier: Operating System :: OS Independent
Requires-Python: >=3.9.0
License-File: LICENSE
Requires-Dist: pymodbus_3p3v==0.1.2
